ctr/__init__.py
ctr/__main__.py
ctr/cli.py
ctr/tests/__init__.py
ctr/tests/test_ctr.py
ctr-0.0.11.dist-info/AUTHORS.rst
ctr-0.0.11.dist-info/LICENSE
ctr-0.0.11.dist-info/METADATA
ctr-0.0.11.dist-info/WHEEL
ctr-0.0.11.dist-info/entry_points.txt
ctr-0.0.11.dist-info/top_level.txt
ctr-0.0.11.dist-info/RECORD
