Metadata-Version: 2.1
Name: ctr
Version: 0.0.11
Summary: Concatenate files w/ headers.
Home-page: https://github.com/samesense/python-ctr
Author: Perry Evans
Author-email: samesense@gmail.com
License: MIT
Project-URL: Documentation, https://python-ctr.readthedocs.io/
Project-URL: Changelog, https://python-ctr.readthedocs.io/en/latest/changelog.html
Project-URL: Issue Tracker, https://github.com/samesense/python-ctr/issues
Platform: UNKNOWN
Classifier: Development Status :: 5 - Production/Stable
Classifier: Intended Audience :: Developers
Classifier: License :: OSI Approved :: MIT License
Classifier: Operating System :: Unix
Classifier: Operating System :: POSIX
Classifier: Operating System :: Microsoft :: Windows
Classifier: Programming Language :: Python :: 3.4
Classifier: Programming Language :: Python :: 3.5
Classifier: Programming Language :: Python :: 3.6
Classifier: Programming Language :: Python :: 3.7
Classifier: Programming Language :: Python :: Implementation :: CPython
Classifier: Programming Language :: Python :: Implementation :: PyPy
Classifier: Topic :: Utilities
Requires-Python: >=3.4, !=3.8.*
Requires-Dist: snakemake (==5.9.1)
